commands/__init__.py
commands/ignore_alert.py
commands/receive_email.py
commands/set_file.py
commands/set_request_header.py
commands/set_user_agent.py
commands/time_execution.py
commands/update_network.py
commands/wait_for_download_finished.py
loadero_py_testui_commands-1.1.0.dist-info/METADATA
loadero_py_testui_commands-1.1.0.dist-info/WHEEL
loadero_py_testui_commands-1.1.0.dist-info/top_level.txt
loadero_py_testui_commands-1.1.0.dist-info/RECORD
