Metadata-Version: 2.1
Name: loadero-py-testui-commands
Version: 1.1.0
Summary: PyTestUI commands for Loadero scripts
Home-page: https://github.com/loadero/loadero-py-testui-commands
Author: Loadero Team
Author-email: support@loadero.com
License: GPLv3
Project-URL: Source, https://github.com/loadero/loadero-py-testui-commands
Project-URL: Tracker, https://github.com/loadero/loadero-py-testui-commands/issues
Project-URL: Loadero, https://loadero.com/
Keywords: loadero
Classifier: Development Status :: 5 - Production/Stable
Classifier: Intended Audience :: Developers
Classifier: Topic :: Software Development :: Quality Assurance
Classifier: License :: OSI Approved :: GNU General Public License v3 (GPLv3)
Classifier: Programming Language :: Python :: 3.6
Classifier: Programming Language :: Python :: 3.7
Classifier: Programming Language :: Python :: 3.8
Classifier: Programming Language :: Python :: 3.9
Classifier: Programming Language :: Python :: 3.10
Classifier: Programming Language :: Python :: 3.11
Requires-Python: >=3.6, <4
Requires-Dist: python-testui
